finometer_logger/finometer.py
finometer_logger-0.1.0.dist-info/METADATA
finometer_logger-0.1.0.dist-info/WHEEL
finometer_logger-0.1.0.dist-info/RECORD
