Metadata-Version: 2.1
Name: finometer-logger
Version: 0.1.0
Summary: A logger that logs finometer data from a serial input.
License: GPL-v3-or-above
Author: Alex
Author-email: adrysdale@protonmail.com
Requires-Python: >=3.10,<3.12
Classifier: License :: Other/Proprietary License
Classifier: Programming Language :: Python :: 3
Classifier: Programming Language :: Python :: 3.10
Classifier: Programming Language :: Python :: 3.11
Requires-Dist: dash (>=2.10.0,<3.0.0)
Requires-Dist: dash-daq (>=0.5.0,<0.6.0)
Requires-Dist: numpy (>=1.24.3,<2.0.0)
Requires-Dist: plotly (>=5.14.1,<6.0.0)
Requires-Dist: serialdatalog (>=0.1.5,<0.2.0)
Requires-Dist: toml (>=0.10.2,<0.11.0)
